{ 
    "_id" : "v4Qybx65NNkWrRQj7", 
    "label" : "IS200"
}
{ 
    "_id" : "sKEXRj89LsSLu6E8y", 
    "label" : "IS201"
}
{ 
    "_id" : "YbCLgw8ydg6qYTb7k", 
    "label" : "IF ELSE"
}
{ 
    "_id" : "qKJnHQ4Qd7p9cAHux", 
    "label" : "INHERITANCE"
}
{ 
    "_id" : "visB5NuXQTaR4jdef", 
    "label" : "EXCEPTIONS"
}
{ 
    "_id" : "hFWBs3EYX3hStnJiW", 
    "label" : "LOOP"
}
{ 
    "_id" : "htX2xpDsYkxzyWpu9", 
    "label" : "STRING"
}
{ 
    "_id" : "wpMuSPucnHXbLwMzo", 
    "label" : "ARRAYS"
}
{ 
    "_id" : "AuDu67FW3Rcf6XwyD", 
    "label" : "SCANNER", 
    "updatedAt" : ISODate("2016-01-21T16:37:31.078+0000")
}
{ 
    "_id" : "MHqayKERZcTuYoJGN", 
    "label" : "CLASS DIAGRAM", 
    "updatedAt" : ISODate("2016-01-07T12:03:21.934+0000")
}
{ 
    "_id" : "QDajzZviT5T8KYgZD", 
    "label" : "ABSTRACT", 
    "updatedAt" : ISODate("2016-01-17T10:21:07.622+0000")
}
{ 
    "_id" : "yo6Mctg4PmmvXWGWZ", 
    "label" : "INTERFACE", 
    "updatedAt" : ISODate("2016-01-21T03:27:19.683+0000")
}
{ 
    "_id" : "9QbeHXdXRdLFSnsWD", 
    "label" : "FENCEPOST", 
    "updatedAt" : ISODate("2016-01-21T06:35:06.988+0000")
}
{ 
    "_id" : "Eqr7mD3xbE9ttHzBn", 
    "label" : "POLYMORPHISM", 
    "updatedAt" : ISODate("2016-01-23T17:13:00.122+0000")
}
{ 
    "_id" : "vutjqoRmWqRTfcKDQ", 
    "label" : "COMPARABLE", 
    "updatedAt" : ISODate("2016-01-23T17:37:16.422+0000")
}
{ 
    "_id" : "ToMpRgDbooKo3Gedj", 
    "label" : "COMPARATOR", 
    "updatedAt" : ISODate("2016-01-23T17:37:23.261+0000")
}
{ 
    "_id" : "WN48SjWjduFPHN6Ab", 
    "label" : "FILE HANDLING", 
    "updatedAt" : ISODate("2016-01-31T05:26:35.534+0000")
}
{ 
    "_id" : "2zr4vZairn2bGqAi9", 
    "label" : "LABTEST", 
    "updatedAt" : ISODate("2016-02-02T09:24:45.997+0000")
}
{ 
    "_id" : "E8h5E7oCPaCrCb8Lh", 
    "label" : "TRY-CATCH", 
    "updatedAt" : ISODate("2016-02-14T11:20:01.863+0000")
}
{ 
    "_id" : "PXmiaqibwSpEirA92", 
    "label" : "HASHMAP", 
    "updatedAt" : ISODate("2016-03-21T04:58:55.665+0000")
}
{ 
    "_id" : "xzuYqC9YogMiw2AB6", 
    "label" : "ARRAYLIST", 
    "updatedAt" : ISODate("2016-04-22T16:42:44.968+0000")
}
{ 
    "_id" : "cbeYMgP22aZfpg8ea", 
    "label" : "CLASS", 
    "updatedAt" : ISODate("2016-04-23T01:23:45.095+0000")
}
{ 
    "_id" : "3JJ5zhLpkdBWufPah", 
    "label" : "UML", 
    "updatedAt" : ISODate("2016-04-25T02:43:20.811+0000")
}
